{
"meta":{"test_sets":[],"test_metrics":[],"learn_metrics":[{"best_value":"Min","name":"RMSE"}],"launch_mode":"Train","parameters":"","iteration_count":500,"learn_sets":["learn"],"name":"experiment"},
"iterations":[
{"learn":[0.476297962],"iteration":0,"passed_time":0.001798692054,"remaining_time":0.8975473352},
{"learn":[0.4436625432],"iteration":1,"passed_time":0.003032562513,"remaining_time":0.7551080658},
{"learn":[0.4161807255],"iteration":2,"passed_time":0.004356970997,"remaining_time":0.7218048618},
{"learn":[0.3945073049],"iteration":3,"passed_time":0.005770543296,"remaining_time":0.7155473688},
{"learn":[0.3728717437],"iteration":4,"passed_time":0.007292822632,"remaining_time":0.7219894406},
{"learn":[0.3541089178],"iteration":5,"passed_time":0.008823099406,"remaining_time":0.7264351844},
{"learn":[0.3380093068],"iteration":6,"passed_time":0.01020118433,"remaining_time":0.7184548389},
{"learn":[0.3222879531],"iteration":7,"passed_time":0.01170690756,"remaining_time":0.7199748149},
{"learn":[0.3082118062],"iteration":8,"passed_time":0.01298590642,"remaining_time":0.7084533392},
{"learn":[0.296882918],"iteration":9,"passed_time":0.01440403472,"remaining_time":0.7057977011},
{"learn":[0.2860343864],"iteration":10,"passed_time":0.01574441743,"remaining_time":0.6999109201},
{"learn":[0.277503319],"iteration":11,"passed_time":0.01697908963,"remaining_time":0.6904829784},
{"learn":[0.2709368743],"iteration":12,"passed_time":0.0181942994,"remaining_time":0.6815864468},
{"learn":[0.2643575521],"iteration":13,"passed_time":0.01944270155,"remaining_time":0.6749394966},
{"learn":[0.260063569],"iteration":14,"passed_time":0.02070439601,"remaining_time":0.6694421377},
{"learn":[0.2542082828],"iteration":15,"passed_time":0.02200219253,"remaining_time":0.6655663239},
{"learn":[0.2496024976],"iteration":16,"passed_time":0.02354517701,"remaining_time":0.6689600292},
{"learn":[0.2460283023],"iteration":17,"passed_time":0.02534532618,"remaining_time":0.6786915122},
{"learn":[0.2430666378],"iteration":18,"passed_time":0.02691445707,"remaining_time":0.681360729},
{"learn":[0.2403150001],"iteration":19,"passed_time":0.02835197218,"remaining_time":0.6804473324},
{"learn":[0.2378936398],"iteration":20,"passed_time":0.02967033688,"remaining_time":0.6767662556},
{"learn":[0.235975651],"iteration":21,"passed_time":0.03112627763,"remaining_time":0.676289123},
{"learn":[0.2321096566],"iteration":22,"passed_time":0.03256436733,"remaining_time":0.6753566615},
{"learn":[0.2303701784],"iteration":23,"passed_time":0.03395685365,"remaining_time":0.6734775973},
{"learn":[0.2274418906],"iteration":24,"passed_time":0.03537602816,"remaining_time":0.6721445351},
{"learn":[0.2260747883],"iteration":25,"passed_time":0.03679189547,"remaining_time":0.6707445558},
{"learn":[0.2247376565],"iteration":26,"passed_time":0.03835289924,"remaining_time":0.6718859756},
{"learn":[0.2225637108],"iteration":27,"passed_time":0.03997257094,"remaining_time":0.6738233387},
{"learn":[0.2212834629],"iteration":28,"passed_time":0.04134643666,"remaining_time":0.6715231609},
{"learn":[0.2188102414],"iteration":29,"passed_time":0.04262741985,"remaining_time":0.6678295776},
{"learn":[0.2166146811],"iteration":30,"passed_time":0.04386145066,"remaining_time":0.6635813019},
{"learn":[0.2157187714],"iteration":31,"passed_time":0.04505968341,"remaining_time":0.6589978698},
{"learn":[0.2140819588],"iteration":32,"passed_time":0.0463654807,"remaining_time":0.6561418027},
{"learn":[0.2134279053],"iteration":33,"passed_time":0.04770224552,"remaining_time":0.6538013651},
{"learn":[0.2123410725],"iteration":34,"passed_time":0.04901877622,"remaining_time":0.6512494555},
{"learn":[0.2116054833],"iteration":35,"passed_time":0.05032667811,"remaining_time":0.6486549623},
{"learn":[0.2106434478],"iteration":36,"passed_time":0.05169949761,"remaining_time":0.6469423619},
{"learn":[0.2091547274],"iteration":37,"passed_time":0.05436392741,"remaining_time":0.6609509069},
{"learn":[0.2081322987],"iteration":38,"passed_time":0.05706782296,"remaining_time":0.6745709329},
{"learn":[0.2070248925],"iteration":39,"passed_time":0.05861616913,"remaining_time":0.674085945},
{"learn":[0.2064905432],"iteration":40,"passed_time":0.0599901044,"remaining_time":0.6715965346},
{"learn":[0.2056219802],"iteration":41,"passed_time":0.06128953842,"remaining_time":0.6683478237},
{"learn":[0.2044484646],"iteration":42,"passed_time":0.06254617853,"remaining_time":0.6647349672},
{"learn":[0.2039051642],"iteration":43,"passed_time":0.06384483025,"remaining_time":0.6616646044},
{"learn":[0.2032467069],"iteration":44,"passed_time":0.06507633555,"remaining_time":0.6579940594},
{"learn":[0.2028197017],"iteration":45,"passed_time":0.06627472865,"remaining_time":0.6541027567},
{"learn":[0.2024133609],"iteration":46,"passed_time":0.06757824035,"remaining_time":0.6513392102},
{"learn":[0.201825221],"iteration":47,"passed_time":0.06887767377,"remaining_time":0.6485980947},
{"learn":[0.2011679737],"iteration":48,"passed_time":0.07010479952,"remaining_time":0.6452502977},
{"learn":[0.2008193518],"iteration":49,"passed_time":0.07135986681,"remaining_time":0.6422388013},
{"learn":[0.2001309773],"iteration":50,"passed_time":0.07258768407,"remaining_time":0.6390562774},
{"learn":[0.1996840628],"iteration":51,"passed_time":0.07388255694,"remaining_time":0.6365266444},
{"learn":[0.1993316777],"iteration":52,"passed_time":0.07508901763,"remaining_time":0.6332979411},
{"learn":[0.1987331847],"iteration":53,"passed_time":0.07633649837,"remaining_time":0.630482931},
{"learn":[0.1983394529],"iteration":54,"passed_time":0.07759981303,"remaining_time":0.6278530327},
{"learn":[0.1978594891],"iteration":55,"passed_time":0.07876753927,"remaining_time":0.6245140613},
{"learn":[0.1974742911],"iteration":56,"passed_time":0.08013412912,"remaining_time":0.6227968281},
{"learn":[0.196661065],"iteration":57,"passed_time":0.08147908179,"remaining_time":0.6209267957},
{"learn":[0.1963376784],"iteration":58,"passed_time":0.08271909565,"remaining_time":0.6182901895},
{"learn":[0.1959051086],"iteration":59,"passed_time":0.08401182445,"remaining_time":0.6160867126},
{"learn":[0.1955491783],"iteration":60,"passed_time":0.0854486769,"remaining_time":0.6149503141},
{"learn":[0.1948195167],"iteration":61,"passed_time":0.08693660133,"remaining_time":0.6141650223},
{"learn":[0.1944896524],"iteration":62,"passed_time":0.08841679891,"remaining_time":0.6133038273},
{"learn":[0.1938782907],"iteration":63,"passed_time":0.08967454142,"remaining_time":0.6109078134},
{"learn":[0.1934992744],"iteration":64,"passed_time":0.09094148399,"remaining_time":0.6086083929},
{"learn":[0.1931007377],"iteration":65,"passed_time":0.09218886421,"remaining_time":0.6062116222},
{"learn":[0.1926631442],"iteration":66,"passed_time":0.09345946506,"remaining_time":0.6039992294},
{"learn":[0.1922275643],"iteration":67,"passed_time":0.09474140974,"remaining_time":0.6018866031},
{"learn":[0.1917705704],"iteration":68,"passed_time":0.09597540077,"remaining_time":0.5994985178},
{"learn":[0.1911509637],"iteration":69,"passed_time":0.09723640038,"remaining_time":0.5973093166},
{"learn":[0.190917375],"iteration":70,"passed_time":0.09836070192,"remaining_time":0.5943202975},
{"learn":[0.1906190469],"iteration":71,"passed_time":0.0997472957,"remaining_time":0.5929422578},
{"learn":[0.190359524],"iteration":72,"passed_time":0.1011213011,"remaining_time":0.5914903504},
{"learn":[0.1896915309],"iteration":73,"passed_time":0.1026321659,"remaining_time":0.5908284143},
{"learn":[0.1891482953],"iteration":74,"passed_time":0.1039641205,"remaining_time":0.5891300162},
{"learn":[0.1885598247],"iteration":75,"passed_time":0.1053196563,"remaining_time":0.5875728191},
{"learn":[0.1882254366],"iteration":76,"passed_time":0.1066565614,"remaining_time":0.5859185125},
{"learn":[0.1878435653],"iteration":77,"passed_time":0.107983154,"remaining_time":0.5842165512},
{"learn":[0.1873239345],"iteration":78,"passed_time":0.1093445024,"remaining_time":0.5827093105},
{"learn":[0.1869602107],"iteration":79,"passed_time":0.1106930931,"remaining_time":0.5811387385},
{"learn":[0.1865658005],"iteration":80,"passed_time":0.1119280659,"remaining_time":0.5789859212},
{"learn":[0.1862114452],"iteration":81,"passed_time":0.1132227286,"remaining_time":0.577159763},
{"learn":[0.1857901548],"iteration":82,"passed_time":0.1145155877,"remaining_time":0.5753373503},
{"learn":[0.1854339768],"iteration":83,"passed_time":0.1158937325,"remaining_time":0.5739499131},
{"learn":[0.1850901783],"iteration":84,"passed_time":0.1173358075,"remaining_time":0.5728748249},
{"learn":[0.1847108677],"iteration":85,"passed_time":0.1187705359,"remaining_time":0.5717558358},
{"learn":[0.1843379615],"iteration":86,"passed_time":0.1201101269,"remaining_time":0.5701779589},
{"learn":[0.1838156862],"iteration":87,"passed_time":0.121421306,"remaining_time":0.5684724779},
{"learn":[0.1836007194],"iteration":88,"passed_time":0.1226549559,"remaining_time":0.5664178302},
{"learn":[0.1832787057],"iteration":89,"passed_time":0.1239480653,"remaining_time":0.5646522973},
{"learn":[0.1829673658],"iteration":90,"passed_time":0.1252474085,"remaining_time":0.5629251656},
{"learn":[0.1823452678],"iteration":91,"passed_time":0.1265810766,"remaining_time":0.5613595569},
{"learn":[0.1817702246],"iteration":92,"passed_time":0.1278624305,"remaining_time":0.5595699918},
{"learn":[0.1812701976],"iteration":93,"passed_time":0.1291934228,"remaining_time":0.5580056346},
{"learn":[0.1808720224],"iteration":94,"passed_time":0.1306465717,"remaining_time":0.5569669635},
{"learn":[0.1805564371],"iteration":95,"passed_time":0.1322682672,"remaining_time":0.5566289578},
{"learn":[0.1801451822],"iteration":96,"passed_time":0.133829452,"remaining_time":0.5560130839},
{"learn":[0.1796621753],"iteration":97,"passed_time":0.1352279511,"remaining_time":0.5547105749},
{"learn":[0.1794215188],"iteration":98,"passed_time":0.1365237265,"remaining_time":0.5529900439},
{"learn":[0.1792088719],"iteration":99,"passed_time":0.137894255,"remaining_time":0.5515770199},
{"learn":[0.1787802746],"iteration":100,"passed_time":0.1392898481,"remaining_time":0.5502638553},
{"learn":[0.1786025483],"iteration":101,"passed_time":0.1405628539,"remaining_time":0.5484707435},
{"learn":[0.178221639],"iteration":102,"passed_time":0.1419087987,"remaining_time":0.5469688649},
{"learn":[0.1779681721],"iteration":103,"passed_time":0.1432508952,"remaining_time":0.5454553315},
{"learn":[0.1776686088],"iteration":104,"passed_time":0.1446415375,"remaining_time":0.5441276885},
{"learn":[0.1773630534],"iteration":105,"passed_time":0.1460730987,"remaining_time":0.5429509517},
{"learn":[0.1770629248],"iteration":106,"passed_time":0.1475449681,"remaining_time":0.5419174996},
{"learn":[0.1765702083],"iteration":107,"passed_time":0.1489809893,"remaining_time":0.5407458132},
{"learn":[0.1762242074],"iteration":108,"passed_time":0.1503896309,"remaining_time":0.5394710613},
{"learn":[0.1759851992],"iteration":109,"passed_time":0.1517639075,"remaining_time":0.5380720357},
{"learn":[0.1756844437],"iteration":110,"passed_time":0.1531075373,"remaining_time":0.5365660541},
{"learn":[0.175313123],"iteration":111,"passed_time":0.1544849708,"remaining_time":0.5351800774},
{"learn":[0.1751372548],"iteration":112,"passed_time":0.1557685997,"remaining_time":0.5334729921},
{"learn":[0.1747886539],"iteration":113,"passed_time":0.1571765698,"remaining_time":0.5321943505},
{"learn":[0.1745056671],"iteration":114,"passed_time":0.1585017801,"remaining_time":0.5306363941},
{"learn":[0.174330532],"iteration":115,"passed_time":0.1598010531,"remaining_time":0.5289965897},
{"learn":[0.1740225939],"iteration":116,"passed_time":0.1611559776,"remaining_time":0.5275447812},
{"learn":[0.1737956828],"iteration":117,"passed_time":0.1625236091,"remaining_time":0.5261357514},
{"learn":[0.1734829087],"iteration":118,"passed_time":0.1639702134,"remaining_time":0.5249802631},
{"learn":[0.1733128858],"iteration":119,"passed_time":0.1654275217,"remaining_time":0.5238538186},
{"learn":[0.1731134241],"iteration":120,"passed_time":0.1668419358,"remaining_time":0.522587551},
{"learn":[0.1727946822],"iteration":121,"passed_time":0.1684576589,"remaining_time":0.5219425825},
{"learn":[0.1725964806],"iteration":122,"passed_time":0.1698404641,"remaining_time":0.5205679266},
{"learn":[0.1722830156],"iteration":123,"passed_time":0.17114102,"remaining_time":0.518943738},
{"learn":[0.172017633],"iteration":124,"passed_time":0.1725172709,"remaining_time":0.5175518127},
{"learn":[0.171777309],"iteration":125,"passed_time":0.1739181655,"remaining_time":0.516233285},
{"learn":[0.1715704566],"iteration":126,"passed_time":0.1753611921,"remaining_time":0.5150372019},
{"learn":[0.1711354761],"iteration":127,"passed_time":0.1767208668,"remaining_time":0.5135950193},
{"learn":[0.1707947535],"iteration":128,"passed_time":0.1783268487,"remaining_time":0.5128624873},
{"learn":[0.1705336154],"iteration":129,"passed_time":0.1798811172,"remaining_time":0.5119693335},
{"learn":[0.170133504],"iteration":130,"passed_time":0.1813383346,"remaining_time":0.5107927136},
{"learn":[0.1699408324],"iteration":131,"passed_time":0.182555208,"remaining_time":0.5089417921},
{"learn":[0.1696731139],"iteration":132,"passed_time":0.1838328139,"remaining_time":0.5072679901},
{"learn":[0.1692738352],"iteration":133,"passed_time":0.1850617235,"remaining_time":0.5054670956},
{"learn":[0.1690256929],"iteration":134,"passed_time":0.1863482488,"remaining_time":0.5038304504},
{"learn":[0.1688022568],"iteration":135,"passed_time":0.1876203626,"remaining_time":0.5021603823},
{"learn":[0.1686073111],"iteration":136,"passed_time":0.1888647861,"remaining_time":0.5004227544},
{"learn":[0.1683983813],"iteration":137,"passed_time":0.1901629067,"remaining_time":0.498833132},
{"learn":[0.1681642499],"iteration":138,"passed_time":0.1913977091,"remaining_time":0.497083259},
{"learn":[0.1679076429],"iteration":139,"passed_time":0.1926373325,"remaining_time":0.4953531406},
{"learn":[0.1676342584],"iteration":140,"passed_time":0.1940124111,"remaining_time":0.4939748624},
{"learn":[0.1674726111],"iteration":141,"passed_time":0.1954284989,"remaining_time":0.4927000184},
{"learn":[0.1672641338],"iteration":142,"passed_time":0.196725467,"remaining_time":0.4911258161},
{"learn":[0.1671281048],"iteration":143,"passed_time":0.1980450136,"remaining_time":0.4896112837},
{"learn":[0.1668011014],"iteration":144,"passed_time":0.1993724782,"remaining_time":0.4881188258},
{"learn":[0.1665907551],"iteration":145,"passed_time":0.2007043423,"remaining_time":0.4866392957},
{"learn":[0.1663426756],"iteration":146,"passed_time":0.2020393035,"remaining_time":0.4851692118},
{"learn":[0.1660648861],"iteration":147,"passed_time":0.2033978361,"remaining_time":0.4837570155},
{"learn":[0.1659454839],"iteration":148,"passed_time":0.2047721628,"remaining_time":0.4823827459},
{"learn":[0.1657201528],"iteration":149,"passed_time":0.2061030348,"remaining_time":0.4809070811},
{"learn":[0.1654584492],"iteration":150,"passed_time":0.2075774194,"remaining_time":0.4797650289},
{"learn":[0.1653207559],"iteration":151,"passed_time":0.2092303132,"remaining_time":0.479027296},
{"learn":[0.1650686743],"iteration":152,"passed_time":0.2108709306,"remaining_time":0.4782497576},
{"learn":[0.1649017637],"iteration":153,"passed_time":0.2124749983,"remaining_time":0.4773788922},
{"learn":[0.1647183246],"iteration":154,"passed_time":0.2138806834,"remaining_time":0.4760570049},
{"learn":[0.1645249702],"iteration":155,"passed_time":0.2152191719,"remaining_time":0.4745858663},
{"learn":[0.164252145],"iteration":156,"passed_time":0.2166000933,"remaining_time":0.4732091211},
{"learn":[0.1640804857],"iteration":157,"passed_time":0.2178727383,"remaining_time":0.4715979526},
{"learn":[0.1639699163],"iteration":158,"passed_time":0.219237264,"remaining_time":0.4701880945},
{"learn":[0.1638159159],"iteration":159,"passed_time":0.2205229374,"remaining_time":0.468611242},
{"learn":[0.163719068],"iteration":160,"passed_time":0.2218748753,"remaining_time":0.4671775325},
{"learn":[0.1635406678],"iteration":161,"passed_time":0.2232542831,"remaining_time":0.4658021463},
{"learn":[0.1633988506],"iteration":162,"passed_time":0.2247407143,"remaining_time":0.4646479799},
{"learn":[0.1632658115],"iteration":163,"passed_time":0.2263800683,"remaining_time":0.4638030668},
{"learn":[0.1630781718],"iteration":164,"passed_time":0.2278474983,"remaining_time":0.4625994663},
{"learn":[0.1628957248],"iteration":165,"passed_time":0.229057597,"remaining_time":0.460874924},
{"learn":[0.162692006],"iteration":166,"passed_time":0.2303564291,"remaining_time":0.4593334783},
{"learn":[0.1625461575],"iteration":167,"passed_time":0.2315684719,"remaining_time":0.4576234088},
{"learn":[0.1623956418],"iteration":168,"passed_time":0.2327349454,"remaining_time":0.4558299819},
{"learn":[0.1622445368],"iteration":169,"passed_time":0.2339707201,"remaining_time":0.4541784566},
{"learn":[0.1619213383],"iteration":170,"passed_time":0.2352197636,"remaining_time":0.4525573229},
{"learn":[0.1617021219],"iteration":171,"passed_time":0.2364231877,"remaining_time":0.4508535207},
{"learn":[0.1615038491],"iteration":172,"passed_time":0.2376421155,"remaining_time":0.449184808},
{"learn":[0.1613707873],"iteration":173,"passed_time":0.2388977134,"remaining_time":0.4475899688},
{"learn":[0.1612496672],"iteration":174,"passed_time":0.2401742669,"remaining_time":0.4460379243},
{"learn":[0.1610994879],"iteration":175,"passed_time":0.241766305,"remaining_time":0.4450697888},
{"learn":[0.1609407173],"iteration":176,"passed_time":0.2435837619,"remaining_time":0.444505961},
{"learn":[0.1607968021],"iteration":177,"passed_time":0.2450982643,"remaining_time":0.4433800062},
{"learn":[0.1606070366],"iteration":178,"passed_time":0.2464824926,"remaining_time":0.4420160901},
{"learn":[0.1604673431],"iteration":179,"passed_time":0.2477370081,"remaining_time":0.4404213477},
{"learn":[0.1603311834],"iteration":180,"passed_time":0.2489932674,"remaining_time":0.4388334381},
{"learn":[0.1601851148],"iteration":181,"passed_time":0.2502595585,"remaining_time":0.4372667012},
{"learn":[0.160085061],"iteration":182,"passed_time":0.2515471255,"remaining_time":0.4357401026},
{"learn":[0.159884802],"iteration":183,"passed_time":0.2528856247,"remaining_time":0.4343035728},
{"learn":[0.1597486037],"iteration":184,"passed_time":0.2541012955,"remaining_time":0.4326589625},
{"learn":[0.1595835308],"iteration":185,"passed_time":0.2553712245,"remaining_time":0.4311105619},
{"learn":[0.1594634866],"iteration":186,"passed_time":0.2569074737,"remaining_time":0.4300109052},
{"learn":[0.1592953401],"iteration":187,"passed_time":0.2585293369,"remaining_time":0.4290486867},
{"learn":[0.1590146125],"iteration":188,"passed_time":0.2600623496,"remaining_time":0.4279332843},
{"learn":[0.1589266389],"iteration":189,"passed_time":0.2617035923,"remaining_time":0.4269900716},
{"learn":[0.1587995288],"iteration":190,"passed_time":0.2630066236,"remaining_time":0.425492391},
{"learn":[0.1586907892],"iteration":191,"passed_time":0.2643089834,"remaining_time":0.4239956608},
{"learn":[0.1585951404],"iteration":192,"passed_time":0.2655285326,"remaining_time":0.4223692202},
{"learn":[0.1585001916],"iteration":193,"passed_time":0.2667911357,"remaining_time":0.4208148841},
{"learn":[0.1582654226],"iteration":194,"passed_time":0.2680392472,"remaining_time":0.4192408738},
{"learn":[0.1581061691],"iteration":195,"passed_time":0.269287038,"remaining_time":0.4176696916},
{"learn":[0.1579724146],"iteration":196,"passed_time":0.2706014842,"remaining_time":0.4162043132},
{"learn":[0.1577928522],"iteration":197,"passed_time":0.2723336311,"remaining_time":0.4153775586},
{"learn":[0.1576588038],"iteration":198,"passed_time":0.2741183488,"remaining_time":0.414621221},
{"learn":[0.1575335334],"iteration":199,"passed_time":0.2753984701,"remaining_time":0.4130977051},
{"learn":[0.1574274904],"iteration":200,"passed_time":0.2765833337,"remaining_time":0.4114349093},
{"learn":[0.1572983241],"iteration":201,"passed_time":0.2778846312,"remaining_time":0.4099486143},
{"learn":[0.1571845007],"iteration":202,"passed_time":0.2791951989,"remaining_time":0.4084777047},
{"learn":[0.1570814494],"iteration":203,"passed_time":0.2804435008,"remaining_time":0.4069180208},
{"learn":[0.1569183725],"iteration":204,"passed_time":0.281722209,"remaining_time":0.40540513},
{"learn":[0.1568133815],"iteration":205,"passed_time":0.2829438528,"remaining_time":0.4038130715},
{"learn":[0.1567377947],"iteration":206,"passed_time":0.2842105348,"remaining_time":0.4022883416},
{"learn":[0.1564899092],"iteration":207,"passed_time":0.2854333311,"remaining_time":0.4007044841},
{"learn":[0.1563445386],"iteration":208,"passed_time":0.2866980489,"remaining_time":0.3991824508},
{"learn":[0.156267764],"iteration":209,"passed_time":0.2883381891,"remaining_time":0.3981813088},
{"learn":[0.1561993708],"iteration":210,"passed_time":0.2898766832,"remaining_time":0.3970348884},
{"learn":[0.156087874],"iteration":211,"passed_time":0.2911397573,"remaining_time":0.3955106138},
{"learn":[0.1559247802],"iteration":212,"passed_time":0.2923831586,"remaining_time":0.3939622841},
{"learn":[0.1557779535],"iteration":213,"passed_time":0.2936163676,"remaining_time":0.3924031829},
{"learn":[0.1557180783],"iteration":214,"passed_time":0.2948456681,"remaining_time":0.3908419321},
{"learn":[0.1556171527],"iteration":215,"passed_time":0.296118243,"remaining_time":0.3893406528},
{"learn":[0.1555545124],"iteration":216,"passed_time":0.2973204243,"remaining_time":0.3877496778},
{"learn":[0.1554716599],"iteration":217,"passed_time":0.2985668221,"remaining_time":0.3862194671},
{"learn":[0.1552950603],"iteration":218,"passed_time":0.2998182909,"remaining_time":0.384698355},
{"learn":[0.1551832653],"iteration":219,"passed_time":0.3011350521,"remaining_time":0.3832627936},
{"learn":[0.1550767448],"iteration":220,"passed_time":0.3024686601,"remaining_time":0.3818495754},
{"learn":[0.1549786684],"iteration":221,"passed_time":0.3040011116,"remaining_time":0.3806860767},
{"learn":[0.1547620805],"iteration":222,"passed_time":0.3054957707,"remaining_time":0.379472325},
{"learn":[0.1546246044],"iteration":223,"passed_time":0.306854794,"remaining_time":0.3780889427},
{"learn":[0.1545449992],"iteration":224,"passed_time":0.3081087282,"remaining_time":0.3765773345},
{"learn":[0.1544553836],"iteration":225,"passed_time":0.309357852,"remaining_time":0.3750621745},
{"learn":[0.1543702004],"iteration":226,"passed_time":0.3105899185,"remaining_time":0.3735288447},
{"learn":[0.1542303502],"iteration":227,"passed_time":0.3118778669,"remaining_time":0.3720648236},
{"learn":[0.1540565646],"iteration":228,"passed_time":0.3132009919,"remaining_time":0.3706439686},
{"learn":[0.1539607466],"iteration":229,"passed_time":0.3144913355,"remaining_time":0.3691854809},
{"learn":[0.1537832752],"iteration":230,"passed_time":0.3157736516,"remaining_time":0.3677191008},
{"learn":[0.15370108],"iteration":231,"passed_time":0.3169730269,"remaining_time":0.3661584966},
{"learn":[0.15362902],"iteration":232,"passed_time":0.3183386607,"remaining_time":0.3647915125},
{"learn":[0.153408752],"iteration":233,"passed_time":0.3198761232,"remaining_time":0.3636198665},
{"learn":[0.1532898203],"iteration":234,"passed_time":0.3215155479,"remaining_time":0.362560086},
{"learn":[0.1531782384],"iteration":235,"passed_time":0.3227988462,"remaining_time":0.3610970144},
{"learn":[0.1531101885],"iteration":236,"passed_time":0.3240840185,"remaining_time":0.3596375395},
{"learn":[0.1530200031],"iteration":237,"passed_time":0.3254225973,"remaining_time":0.3582383214},
{"learn":[0.1528895304],"iteration":238,"passed_time":0.32666209,"remaining_time":0.3567314037},
{"learn":[0.1527668743],"iteration":239,"passed_time":0.3278985962,"remaining_time":0.3552234792},
{"learn":[0.1526374843],"iteration":240,"passed_time":0.3291750495,"remaining_time":0.3537607378},
{"learn":[0.152515666],"iteration":241,"passed_time":0.3304880525,"remaining_time":0.3523385023},
{"learn":[0.1524215064],"iteration":242,"passed_time":0.3317790776,"remaining_time":0.3508939216},
{"learn":[0.1523150272],"iteration":243,"passed_time":0.3330698221,"remaining_time":0.3494503051},
{"learn":[0.1522046267],"iteration":244,"passed_time":0.3347152539,"remaining_time":0.348377101},
{"learn":[0.1520246569],"iteration":245,"passed_time":0.3362031482,"remaining_time":0.3471365839},
{"learn":[0.1519176205],"iteration":246,"passed_time":0.3375045459,"remaining_time":0.3457030369},
{"learn":[0.1518494654],"iteration":247,"passed_time":0.3387352094,"remaining_time":0.3441986805},
{"learn":[0.1517268277],"iteration":248,"passed_time":0.340089302,"remaining_time":0.342820943},
{"learn":[0.1515944066],"iteration":249,"passed_time":0.3413559038,"remaining_time":0.3413559038},
{"learn":[0.1515467227],"iteration":250,"passed_time":0.3425697105,"remaining_time":0.3398400714},
{"learn":[0.1514598008],"iteration":251,"passed_time":0.3438812403,"remaining_time":0.338422808},
{"learn":[0.1513558294],"iteration":252,"passed_time":0.3451475816,"remaining_time":0.3369622635},
{"learn":[0.151292032],"iteration":253,"passed_time":0.346436933,"remaining_time":0.3355255336},
{"learn":[0.1512077208],"iteration":254,"passed_time":0.3477282588,"remaining_time":0.3340918565},
{"learn":[0.1510970339],"iteration":255,"passed_time":0.3489837364,"remaining_time":0.3326251237},
{"learn":[0.1509771795],"iteration":256,"passed_time":0.3505995056,"remaining_time":0.3315006998},
{"learn":[0.1508068116],"iteration":257,"passed_time":0.3519790437,"remaining_time":0.3301508859},
{"learn":[0.1506973791],"iteration":258,"passed_time":0.3536663228,"remaining_time":0.3290871961},
{"learn":[0.1504657949],"iteration":259,"passed_time":0.3551814004,"remaining_time":0.3278597542},
{"learn":[0.150415103],"iteration":260,"passed_time":0.3564924191,"remaining_time":0.3264432496},
{"learn":[0.1503213771],"iteration":261,"passed_time":0.3577635007,"remaining_time":0.3249912716},
{"learn":[0.1502420972],"iteration":262,"passed_time":0.3589978221,"remaining_time":0.3235075431},
{"learn":[0.1501296575],"iteration":263,"passed_time":0.3602592627,"remaining_time":0.3220499469},
{"learn":[0.1499722799],"iteration":264,"passed_time":0.3614773888,"remaining_time":0.3205554203},
{"learn":[0.1498183916],"iteration":265,"passed_time":0.3628338365,"remaining_time":0.3191846532},
{"learn":[0.149687039],"iteration":266,"passed_time":0.3641585351,"remaining_time":0.3177862871},
{"learn":[0.1496173479],"iteration":267,"passed_time":0.3654042213,"remaining_time":0.3163200722},
{"learn":[0.1495057306],"iteration":268,"passed_time":0.3669061323,"remaining_time":0.3150755262},
{"learn":[0.1494342305],"iteration":269,"passed_time":0.3684627604,"remaining_time":0.3138756848},
{"learn":[0.1493462611],"iteration":270,"passed_time":0.3697780184,"remaining_time":0.312469248},
{"learn":[0.1492157045],"iteration":271,"passed_time":0.3712774378,"remaining_time":0.3112178523},
{"learn":[0.1491194877],"iteration":272,"passed_time":0.3726483772,"remaining_time":0.3098578081},
{"learn":[0.1490374903],"iteration":273,"passed_time":0.3739828169,"remaining_time":0.3084675789},
{"learn":[0.1489093628],"iteration":274,"passed_time":0.3754674542,"remaining_time":0.3072006443},
{"learn":[0.1488448534],"iteration":275,"passed_time":0.3769107513,"remaining_time":0.3058985808},
{"learn":[0.1487198537],"iteration":276,"passed_time":0.3784933616,"remaining_time":0.3047076521},
{"learn":[0.1486163123],"iteration":277,"passed_time":0.3800166999,"remaining_time":0.3034665733},
{"learn":[0.148517869],"iteration":278,"passed_time":0.3819132693,"remaining_time":0.302519113},
{"learn":[0.1483343243],"iteration":279,"passed_time":0.3834152644,"remaining_time":0.3012548506},
{"learn":[0.1481639962],"iteration":280,"passed_time":0.3849469543,"remaining_time":0.3000120391},
{"learn":[0.1480779327],"iteration":281,"passed_time":0.3863594542,"remaining_time":0.2986750391},
{"learn":[0.1480014994],"iteration":282,"passed_time":0.3877107708,"remaining_time":0.297290591},
{"learn":[0.1479105159],"iteration":283,"passed_time":0.3891836424,"remaining_time":0.2959988266},
{"learn":[0.1478275385],"iteration":284,"passed_time":0.3905014058,"remaining_time":0.2945887798},
{"learn":[0.1477478633],"iteration":285,"passed_time":0.3917558171,"remaining_time":0.293131975},
{"learn":[0.1476830105],"iteration":286,"passed_time":0.3930311419,"remaining_time":0.2916921018},
{"learn":[0.147594178],"iteration":287,"passed_time":0.3942461813,"remaining_time":0.2902089945},
{"learn":[0.1475209309],"iteration":288,"passed_time":0.3955729844,"remaining_time":0.2888093415},
{"learn":[0.1474498847],"iteration":289,"passed_time":0.396867457,"remaining_time":0.2873867792},
{"learn":[0.1473886039],"iteration":290,"passed_time":0.3983369011,"remaining_time":0.286090764},
{"learn":[0.1473296521],"iteration":291,"passed_time":0.3997995604,"remaining_time":0.284788728},
{"learn":[0.1471551723],"iteration":292,"passed_time":0.4012063774,"remaining_time":0.2834461438},
{"learn":[0.1470950305],"iteration":293,"passed_time":0.4025632962,"remaining_time":0.2820681599},
{"learn":[0.1470249328],"iteration":294,"passed_time":0.4039058336,"remaining_time":0.280680325},
{"learn":[0.1469323614],"iteration":295,"passed_time":0.4051512793,"remaining_time":0.2792258817},
{"learn":[0.1468822514],"iteration":296,"passed_time":0.4063445612,"remaining_time":0.2777371917},
{"learn":[0.1468214306],"iteration":297,"passed_time":0.4075978841,"remaining_time":0.2762911832},
{"learn":[0.1467036998],"iteration":298,"passed_time":0.4088465268,"remaining_time":0.2748433173},
{"learn":[0.1466459172],"iteration":299,"passed_time":0.4101137199,"remaining_time":0.2734091466},
{"learn":[0.1465611359],"iteration":300,"passed_time":0.411379971,"remaining_time":0.2719754625},
{"learn":[0.1464028548],"iteration":301,"passed_time":0.4129157758,"remaining_time":0.2707196146},
{"learn":[0.1462634363],"iteration":302,"passed_time":0.4145615584,"remaining_time":0.2695334225},
{"learn":[0.1461767521],"iteration":303,"passed_time":0.4159067817,"remaining_time":0.268150425},
{"learn":[0.1460867974],"iteration":304,"passed_time":0.4172068365,"remaining_time":0.2667387971},
{"learn":[0.1460184646],"iteration":305,"passed_time":0.418473288,"remaining_time":0.2653065943},
{"learn":[0.1459609479],"iteration":306,"passed_time":0.4196709094,"remaining_time":0.2638322004},
{"learn":[0.1458556942],"iteration":307,"passed_time":0.4209186401,"remaining_time":0.2623908406},
{"learn":[0.145797906],"iteration":308,"passed_time":0.4221606182,"remaining_time":0.2609471782},
{"learn":[0.1457600976],"iteration":309,"passed_time":0.4233582196,"remaining_time":0.2594776184},
{"learn":[0.145715873],"iteration":310,"passed_time":0.4246426102,"remaining_time":0.2580625509},
{"learn":[0.1456028745],"iteration":311,"passed_time":0.4259121284,"remaining_time":0.2566393594},
{"learn":[0.1455140205],"iteration":312,"passed_time":0.4271330306,"remaining_time":0.2551881045},
{"learn":[0.1454024453],"iteration":313,"passed_time":0.4285217186,"remaining_time":0.2538377059},
{"learn":[0.1452566191],"iteration":314,"passed_time":0.4300822975,"remaining_time":0.252588016},
{"learn":[0.145192535],"iteration":315,"passed_time":0.4317465965,"remaining_time":0.2513967524},
{"learn":[0.1451539182],"iteration":316,"passed_time":0.4330571041,"remaining_time":0.2499982651},
{"learn":[0.1451167335],"iteration":317,"passed_time":0.4343069694,"remaining_time":0.248565624},
{"learn":[0.1450299654],"iteration":318,"passed_time":0.4355832824,"remaining_time":0.2471491352},
{"learn":[0.1448945365],"iteration":319,"passed_time":0.4369219414,"remaining_time":0.245768592},
{"learn":[0.1447801004],"iteration":320,"passed_time":0.4383418575,"remaining_time":0.2444336215},
{"learn":[0.1446846506],"iteration":321,"passed_time":0.4397597231,"remaining_time":0.2430969898},
{"learn":[0.1446337427],"iteration":322,"passed_time":0.4410294718,"remaining_time":0.2416786889},
{"learn":[0.1445576144],"iteration":323,"passed_time":0.4422506847,"remaining_time":0.2402349398},
{"learn":[0.1444332854],"iteration":324,"passed_time":0.443599135,"remaining_time":0.2388610727},
{"learn":[0.1443690233],"iteration":325,"passed_time":0.4449592607,"remaining_time":0.2374935931},
{"learn":[0.1443197035],"iteration":326,"passed_time":0.4462516688,"remaining_time":0.2360903324},
{"learn":[0.1442393824],"iteration":327,"passed_time":0.44751339,"remaining_time":0.2346716557},
{"learn":[0.1441688872],"iteration":328,"passed_time":0.4488111498,"remaining_time":0.2332726645},
{"learn":[0.1441202605],"iteration":329,"passed_time":0.4500716182,"remaining_time":0.2318550761},
{"learn":[0.1440598248],"iteration":330,"passed_time":0.4513469992,"remaining_time":0.230446051},
{"learn":[0.1440091501],"iteration":331,"passed_time":0.4525823228,"remaining_time":0.229017561},
{"learn":[0.1439482483],"iteration":332,"passed_time":0.453790377,"remaining_time":0.2275765554},
{"learn":[0.1438660183],"iteration":333,"passed_time":0.4551009708,"remaining_time":0.2261879077},
{"learn":[0.1437904912],"iteration":334,"passed_time":0.4563705892,"remaining_time":0.2247795439},
{"learn":[0.1436833332],"iteration":335,"passed_time":0.4576305566,"remaining_time":0.2233672955},
{"learn":[0.1436249326],"iteration":336,"passed_time":0.4591926728,"remaining_time":0.222102094},
{"learn":[0.1435326885],"iteration":337,"passed_time":0.4607624757,"remaining_time":0.2208388197},
{"learn":[0.1434879876],"iteration":338,"passed_time":0.462145335,"remaining_time":0.2194849526},
{"learn":[0.1434349023],"iteration":339,"passed_time":0.4635109528,"remaining_time":0.2181228013},
{"learn":[0.1433714709],"iteration":340,"passed_time":0.4650662702,"remaining_time":0.216849082},
{"learn":[0.1432867942],"iteration":341,"passed_time":0.4664338522,"remaining_time":0.2154869844},
{"learn":[0.1432177603],"iteration":342,"passed_time":0.4677377153,"remaining_time":0.2140956889},
{"learn":[0.143124244],"iteration":343,"passed_time":0.4690818695,"remaining_time":0.2127231734},
{"learn":[0.1430662939],"iteration":344,"passed_time":0.4703593657,"remaining_time":0.2113208745},
{"learn":[0.1430402145],"iteration":345,"passed_time":0.471616547,"remaining_time":0.209910255},
{"learn":[0.1429882406],"iteration":346,"passed_time":0.4727885827,"remaining_time":0.2084629774},
{"learn":[0.1429536072],"iteration":347,"passed_time":0.4739227156,"remaining_time":0.2070007264},
{"learn":[0.1428307267],"iteration":348,"passed_time":0.4752895761,"remaining_time":0.2056410487},
{"learn":[0.1427088601],"iteration":349,"passed_time":0.4767246553,"remaining_time":0.2043105665},
{"learn":[0.1426554823],"iteration":350,"passed_time":0.4780919567,"remaining_time":0.2029507167},
{"learn":[0.142604783],"iteration":351,"passed_time":0.4794122356,"remaining_time":0.2015710536},
{"learn":[0.1425606803],"iteration":352,"passed_time":0.4807058864,"remaining_time":0.2001806382},
{"learn":[0.1425097325],"iteration":353,"passed_time":0.4820243407,"remaining_time":0.1988009993},
{"learn":[0.1424391123],"iteration":354,"passed_time":0.4832393105,"remaining_time":0.1973794367},
{"learn":[0.1423604536],"iteration":355,"passed_time":0.4844690119,"remaining_time":0.1959649936},
{"learn":[0.1423090224],"iteration":356,"passed_time":0.4856726464,"remaining_time":0.1945411441},
{"learn":[0.1422610744],"iteration":357,"passed_time":0.4867827269,"remaining_time":0.1930814168},
{"learn":[0.1422201473],"iteration":358,"passed_time":0.4879806691,"remaining_time":0.1916581458},
{"learn":[0.1421527943],"iteration":359,"passed_time":0.4891587178,"remaining_time":0.1902283903},
{"learn":[0.1420687379],"iteration":360,"passed_time":0.4904436696,"remaining_time":0.1888411914},
{"learn":[0.1420140423],"iteration":361,"passed_time":0.4917955675,"remaining_time":0.1874800782},
{"learn":[0.1419776502],"iteration":362,"passed_time":0.4930949808,"remaining_time":0.1860992076},
{"learn":[0.1419158368],"iteration":363,"passed_time":0.4943752324,"remaining_time":0.1847116253},
{"learn":[0.14184331],"iteration":364,"passed_time":0.4956047835,"remaining_time":0.1833058788},
{"learn":[0.1417832116],"iteration":365,"passed_time":0.4967959107,"remaining_time":0.1818870274},
{"learn":[0.1416995724],"iteration":366,"passed_time":0.4979937326,"remaining_time":0.1804718431},
{"learn":[0.1416489066],"iteration":367,"passed_time":0.4992380659,"remaining_time":0.1790745236},
{"learn":[0.141586885],"iteration":368,"passed_time":0.5004877809,"remaining_time":0.1776799439},
{"learn":[0.1415153812],"iteration":369,"passed_time":0.5016987614,"remaining_time":0.1762725378},
{"learn":[0.1414757662],"iteration":370,"passed_time":0.5029002011,"remaining_time":0.1748628732},
{"learn":[0.1414083377],"iteration":371,"passed_time":0.5041484429,"remaining_time":0.173470432},
{"learn":[0.1413508191],"iteration":372,"passed_time":0.5053010763,"remaining_time":0.172046211},
{"learn":[0.1413145283],"iteration":373,"passed_time":0.5066296031,"remaining_time":0.1706827005},
{"learn":[0.1412393564],"iteration":374,"passed_time":0.5080110454,"remaining_time":0.1693370151},
{"learn":[0.1411754437],"iteration":375,"passed_time":0.5093100378,"remaining_time":0.1679639486},
{"learn":[0.1411248056],"iteration":376,"passed_time":0.510559362,"remaining_time":0.1665750704},
{"learn":[0.1410552084],"iteration":377,"passed_time":0.5118691179,"remaining_time":0.1652064349},
{"learn":[0.1409907077],"iteration":378,"passed_time":0.5131706158,"remaining_time":0.1638354737},
{"learn":[0.1409247816],"iteration":379,"passed_time":0.514527264,"remaining_time":0.1624822939},
{"learn":[0.1408634788],"iteration":380,"passed_time":0.5157511427,"remaining_time":0.1610876272},
{"learn":[0.1408069666],"iteration":381,"passed_time":0.5169305945,"remaining_time":0.1596801313},
{"learn":[0.1407179201],"iteration":382,"passed_time":0.5181466361,"remaining_time":0.1582850037},
{"learn":[0.1406605359],"iteration":383,"passed_time":0.5193250957,"remaining_time":0.156879456},
{"learn":[0.1405853378],"iteration":384,"passed_time":0.5205263049,"remaining_time":0.1554818833},
{"learn":[0.1405369638],"iteration":385,"passed_time":0.5218725398,"remaining_time":0.1541281594},
{"learn":[0.1404920179],"iteration":386,"passed_time":0.523639192,"remaining_time":0.1528972318},
{"learn":[0.1404133429],"iteration":387,"passed_time":0.5250749226,"remaining_time":0.1515680189},
{"learn":[0.140348613],"iteration":388,"passed_time":0.5263464853,"remaining_time":0.1501914135},
{"learn":[0.1403032518],"iteration":389,"passed_time":0.5276389635,"remaining_time":0.1488212461},
{"learn":[0.1402764927],"iteration":390,"passed_time":0.5288961348,"remaining_time":0.1474416335},
{"learn":[0.1402103982],"iteration":391,"passed_time":0.5301627767,"remaining_time":0.1460652548},
{"learn":[0.1401783719],"iteration":392,"passed_time":0.5313833882,"remaining_time":0.1446769021},
{"learn":[0.1401200435],"iteration":393,"passed_time":0.5325635516,"remaining_time":0.143278519},
{"learn":[0.1400582645],"iteration":394,"passed_time":0.5338265856,"remaining_time":0.1419032696},
{"learn":[0.1400107072],"iteration":395,"passed_time":0.5350740457,"remaining_time":0.1405244969},
{"learn":[0.1399266898],"iteration":396,"passed_time":0.5362923923,"remaining_time":0.1391388323},
{"learn":[0.1398821969],"iteration":397,"passed_time":0.5375640245,"remaining_time":0.1377676646},
{"learn":[0.1398343035],"iteration":398,"passed_time":0.5389600987,"remaining_time":0.1364284962},
{"learn":[0.1397190946],"iteration":399,"passed_time":0.5402745053,"remaining_time":0.1350686263},
{"learn":[0.1395931331],"iteration":400,"passed_time":0.5415797013,"remaining_time":0.1337067093},
{"learn":[0.1395415225],"iteration":401,"passed_time":0.5428505925,"remaining_time":0.1323367116},
{"learn":[0.1394883334],"iteration":402,"passed_time":0.5441620522,"remaining_time":0.1309769704},
{"learn":[0.1393713363],"iteration":403,"passed_time":0.5454653941,"remaining_time":0.1296155392},
{"learn":[0.1393316908],"iteration":404,"passed_time":0.5467120524,"remaining_time":0.1282410987},
{"learn":[0.1392878943],"iteration":405,"passed_time":0.548015655,"remaining_time":0.1268804718},
{"learn":[0.1392541536],"iteration":406,"passed_time":0.5492499463,"remaining_time":0.1255042875},
{"learn":[0.1392181373],"iteration":407,"passed_time":0.5504996413,"remaining_time":0.1241322721},
{"learn":[0.1391954191],"iteration":408,"passed_time":0.5517966695,"remaining_time":0.1227713861},
{"learn":[0.1391203779],"iteration":409,"passed_time":0.5533747566,"remaining_time":0.1214725075},
{"learn":[0.1390879784],"iteration":410,"passed_time":0.5547944923,"remaining_time":0.1201379801},
{"learn":[0.1390329242],"iteration":411,"passed_time":0.5561755537,"remaining_time":0.1187947785},
{"learn":[0.1389849424],"iteration":412,"passed_time":0.557484117,"remaining_time":0.1174361215},
{"learn":[0.1389338294],"iteration":413,"passed_time":0.5591299959,"remaining_time":0.1161477769},
{"learn":[0.1388948714],"iteration":414,"passed_time":0.5604525497,"remaining_time":0.1147914861},
{"learn":[0.1388409328],"iteration":415,"passed_time":0.5618120581,"remaining_time":0.1134428194},
{"learn":[0.1387850186],"iteration":416,"passed_time":0.5631179115,"remaining_time":0.1120834212},
{"learn":[0.1387320775],"iteration":417,"passed_time":0.5644157014,"remaining_time":0.1107226974},
{"learn":[0.1386697648],"iteration":418,"passed_time":0.5658516163,"remaining_time":0.1093889759},
{"learn":[0.1385987955],"iteration":419,"passed_time":0.5671134678,"remaining_time":0.1080216129},
{"learn":[0.1385347004],"iteration":420,"passed_time":0.5684257993,"remaining_time":0.1066642236},
{"learn":[0.1385017625],"iteration":421,"passed_time":0.5698990317,"remaining_time":0.1053367879},
{"learn":[0.1384500814],"iteration":422,"passed_time":0.5713450748,"remaining_time":0.1040037134},
{"learn":[0.1384031023],"iteration":423,"passed_time":0.5726702544,"remaining_time":0.1026484418},
{"learn":[0.1382932173],"iteration":424,"passed_time":0.573943611,"remaining_time":0.1012841666},
{"learn":[0.1382329902],"iteration":425,"passed_time":0.5753338824,"remaining_time":0.09994062747},
{"learn":[0.1382159323],"iteration":426,"passed_time":0.5765966058,"remaining_time":0.09857506376},
{"learn":[0.1381517241],"iteration":427,"passed_time":0.5779201278,"remaining_time":0.09722020842},
{"learn":[0.1381155507],"iteration":428,"passed_time":0.5793142176,"remaining_time":0.09587717821},
{"learn":[0.1380904314],"iteration":429,"passed_time":0.5806332076,"remaining_time":0.09452168497},
{"learn":[0.138063129],"iteration":430,"passed_time":0.581902325,"remaining_time":0.09315837685},
{"learn":[0.1380201699],"iteration":431,"passed_time":0.5832144861,"remaining_time":0.09180228022},
{"learn":[0.1379631122],"iteration":432,"passed_time":0.5845234904,"remaining_time":0.09044589806},
{"learn":[0.1379032498],"iteration":433,"passed_time":0.5860121064,"remaining_time":0.08911704843},
{"learn":[0.1378497675],"iteration":434,"passed_time":0.5876761743,"remaining_time":0.08781368121},
{"learn":[0.1378044211],"iteration":435,"passed_time":0.5889273324,"remaining_time":0.08644804879},
{"learn":[0.1377634114],"iteration":436,"passed_time":0.5901582665,"remaining_time":0.08508002468},
{"learn":[0.1377270495],"iteration":437,"passed_time":0.5913729651,"remaining_time":0.0837103284},
{"learn":[0.1376986937],"iteration":438,"passed_time":0.592542846,"remaining_time":0.08233511073},
{"learn":[0.1376798385],"iteration":439,"passed_time":0.5937161645,"remaining_time":0.08096129516},
{"learn":[0.1376544493],"iteration":440,"passed_time":0.594889533,"remaining_time":0.07958839557},
{"learn":[0.137620181],"iteration":441,"passed_time":0.5960292882,"remaining_time":0.07821198805},
{"learn":[0.13755714],"iteration":442,"passed_time":0.5972961607,"remaining_time":0.07685300487},
{"learn":[0.1375313705],"iteration":443,"passed_time":0.5984830292,"remaining_time":0.07548434603},
{"learn":[0.1374667765],"iteration":444,"passed_time":0.5997105058,"remaining_time":0.07412152318},
{"learn":[0.1374442171],"iteration":445,"passed_time":0.6013900073,"remaining_time":0.07281403676},
{"learn":[0.1373939855],"iteration":446,"passed_time":0.6027802387,"remaining_time":0.07147058759},
{"learn":[0.1373425115],"iteration":447,"passed_time":0.6040536751,"remaining_time":0.07011337301},
{"learn":[0.1372990953],"iteration":448,"passed_time":0.6054167977,"remaining_time":0.06876671867},
{"learn":[0.1372399216],"iteration":449,"passed_time":0.6066287103,"remaining_time":0.06740319004},
{"learn":[0.1371780565],"iteration":450,"passed_time":0.6079122892,"remaining_time":0.06604812011},
{"learn":[0.1371344907],"iteration":451,"passed_time":0.6091416298,"remaining_time":0.0646876067},
{"learn":[0.1370688209],"iteration":452,"passed_time":0.6104602951,"remaining_time":0.06333694011},
{"learn":[0.1369796098],"iteration":453,"passed_time":0.6117428818,"remaining_time":0.06198275895},
{"learn":[0.1369418335],"iteration":454,"passed_time":0.6129196578,"remaining_time":0.06061842769},
{"learn":[0.1368496556],"iteration":455,"passed_time":0.6141593215,"remaining_time":0.05926098716},
{"learn":[0.1367862319],"iteration":456,"passed_time":0.6153937932,"remaining_time":0.05790357354},
{"learn":[0.1367233886],"iteration":457,"passed_time":0.6171612132,"remaining_time":0.05659556976},
{"learn":[0.1366817736],"iteration":458,"passed_time":0.6188794598,"remaining_time":0.05528117179},
{"learn":[0.1366196822],"iteration":459,"passed_time":0.6200985079,"remaining_time":0.05392160939},
{"learn":[0.1365499309],"iteration":460,"passed_time":0.6213701708,"remaining_time":0.05256710772},
{"learn":[0.1365069417],"iteration":461,"passed_time":0.6227022153,"remaining_time":0.05121793113},
{"learn":[0.1364564051],"iteration":462,"passed_time":0.6239236086,"remaining_time":0.049859986},
{"learn":[0.136435323],"iteration":463,"passed_time":0.6252359,"remaining_time":0.0485096819},
{"learn":[0.1362838016],"iteration":464,"passed_time":0.6265542748,"remaining_time":0.04715999918},
{"learn":[0.1362345873],"iteration":465,"passed_time":0.627815555,"remaining_time":0.04580628513},
{"learn":[0.1361123495],"iteration":466,"passed_time":0.6291244089,"remaining_time":0.04445632868},
{"learn":[0.1360672517],"iteration":467,"passed_time":0.6303430562,"remaining_time":0.04310037991},
{"learn":[0.1360398405],"iteration":468,"passed_time":0.6315279098,"remaining_time":0.04174278295},
{"learn":[0.1360053554],"iteration":469,"passed_time":0.6328528321,"remaining_time":0.04039486162},
{"learn":[0.1359376518],"iteration":470,"passed_time":0.6344254679,"remaining_time":0.03906228996},
{"learn":[0.1358975146],"iteration":471,"passed_time":0.635696319,"remaining_time":0.03771079859},
{"learn":[0.1358524417],"iteration":472,"passed_time":0.636970307,"remaining_time":0.03635982725},
{"learn":[0.1358054548],"iteration":473,"passed_time":0.6382564013,"remaining_time":0.0350098448},
{"learn":[0.1357637336],"iteration":474,"passed_time":0.6395562456,"remaining_time":0.03366085503},
{"learn":[0.1357236832],"iteration":475,"passed_time":0.6407988551,"remaining_time":0.03230918597},
{"learn":[0.135659621],"iteration":476,"passed_time":0.64200266,"remaining_time":0.0309561031},
{"learn":[0.1356129352],"iteration":477,"passed_time":0.6432361296,"remaining_time":0.02960501015},
{"learn":[0.135586895],"iteration":478,"passed_time":0.6445188466,"remaining_time":0.02825656739},
{"learn":[0.1355535874],"iteration":479,"passed_time":0.6457459022,"remaining_time":0.02690607926},
{"learn":[0.1354930867],"iteration":480,"passed_time":0.6470268152,"remaining_time":0.02555823179},
{"learn":[0.1354696377],"iteration":481,"passed_time":0.6486293996,"remaining_time":0.02422267468},
{"learn":[0.1354302362],"iteration":482,"passed_time":0.6500747813,"remaining_time":0.02288047885},
{"learn":[0.1353704481],"iteration":483,"passed_time":0.6513405613,"remaining_time":0.02153191938},
{"learn":[0.1353018779],"iteration":484,"passed_time":0.652527279,"remaining_time":0.02018125605},
{"learn":[0.1352268433],"iteration":485,"passed_time":0.6537350425,"remaining_time":0.01883187365},
{"learn":[0.135191757],"iteration":486,"passed_time":0.6549172904,"remaining_time":0.01748239174},
{"learn":[0.1351589633],"iteration":487,"passed_time":0.6562237592,"remaining_time":0.01613664982},
{"learn":[0.1350723803],"iteration":488,"passed_time":0.657524315,"remaining_time":0.01479093551},
{"learn":[0.1350439951],"iteration":489,"passed_time":0.6587569729,"remaining_time":0.01344401985},
{"learn":[0.1349990045],"iteration":490,"passed_time":0.6599904124,"remaining_time":0.01209758393},
{"learn":[0.134926106],"iteration":491,"passed_time":0.6612107032,"remaining_time":0.01075139355},
{"learn":[0.1348780012],"iteration":492,"passed_time":0.6625344135,"remaining_time":0.009407182342},
{"learn":[0.1348317377],"iteration":493,"passed_time":0.6641287761,"remaining_time":0.00806634141},
{"learn":[0.134786331],"iteration":494,"passed_time":0.6656090739,"remaining_time":0.006723323979},
{"learn":[0.1347666867],"iteration":495,"passed_time":0.6672493906,"remaining_time":0.005381043473},
{"learn":[0.1347327664],"iteration":496,"passed_time":0.6688510269,"remaining_time":0.004037330142},
{"learn":[0.1346676871],"iteration":497,"passed_time":0.6701963704,"remaining_time":0.002691551689},
{"learn":[0.1346012725],"iteration":498,"passed_time":0.6714778247,"remaining_time":0.001345646943},
{"learn":[0.134564052],"iteration":499,"passed_time":0.6727546889,"remaining_time":0}
]}